graphenex/__init__.py
graphenex/__main__.py
graphenex/core/cli/commands.py
graphenex/core/cli/help.py
graphenex/core/cli/shell.py
graphenex/core/hrd/__init__.py
graphenex/core/hrd/exec.py
graphenex/core/utils/helpers.py
graphenex/core/utils/logcl.py
graphenex/core/utils/sysinfo.py
graphenex/core/web/__init__.py
graphenex/core/web/providers.py
graphenex/core/web/static/css/aos.css
graphenex/core/web/static/css/bootstrap.min.css
graphenex/core/web/static/css/fa_all.css
graphenex/core/web/static/css/index.css
graphenex/core/web/static/images/favicon.ico
graphenex/core/web/static/images/graphenex_logo_white.png
graphenex/core/web/static/js/aos.js
graphenex/core/web/static/js/bootstrap.min.js
graphenex/core/web/static/js/index.js
graphenex/core/web/static/js/jquery-3.7.1.js
graphenex/core/web/static/js/listgroup.min.js
graphenex/core/web/static/js/popper.min.js
graphenex/core/web/static/js/providers.js
graphenex/core/web/static/js/socket.io.min.js
graphenex/core/web/static/js/template.js
graphenex/core/web/static/webfonts/fa-brands-400.eot
graphenex/core/web/static/webfonts/fa-brands-400.svg
graphenex/core/web/static/webfonts/fa-brands-400.ttf
graphenex/core/web/static/webfonts/fa-brands-400.woff
graphenex/core/web/static/webfonts/fa-brands-400.woff2
graphenex/core/web/static/webfonts/fa-regular-400.eot
graphenex/core/web/static/webfonts/fa-regular-400.svg
graphenex/core/web/static/webfonts/fa-regular-400.ttf
graphenex/core/web/static/webfonts/fa-regular-400.woff
graphenex/core/web/static/webfonts/fa-regular-400.woff2
graphenex/core/web/static/webfonts/fa-solid-900.eot
graphenex/core/web/static/webfonts/fa-solid-900.svg
graphenex/core/web/static/webfonts/fa-solid-900.ttf
graphenex/core/web/static/webfonts/fa-solid-900.woff
graphenex/core/web/static/webfonts/fa-solid-900.woff2
graphenex/core/web/templates/404.html
graphenex/core/web/templates/auth.html
graphenex/core/web/templates/index.html
graphenex/core/web/views.py
graphenex/modules.json
graphenex-1.7.0.dist-info/LICENSE
graphenex-1.7.0.dist-info/METADATA
graphenex-1.7.0.dist-info/WHEEL
graphenex-1.7.0.dist-info/entry_points.txt
graphenex-1.7.0.dist-info/RECORD
