Metadata-Version: 2.1
Name: GrapheneX
Version: 1.7.0
Summary: Automated System Hardening Framework for Linux & Windows
Home-page: https://graphenex.github.io
License: GPL-3.0-or-later
Keywords: hardening,hardening-commands,security
Author: grapheneX contributors
Author-email: graphenex.project@protonmail.com
Requires-Python: >=3.10,<4.0
Classifier: Intended Audience :: Developers
Classifier: Intended Audience :: End Users/Desktop
Classifier: Intended Audience :: System Administrators
Classifier: License :: OSI Approved :: GNU General Public License v3 (GPLv3)
Classifier: License :: OSI Approved :: GNU General Public License v3 or later (GPLv3+)
Classifier: Natural Language :: English
Classifier: Operating System :: OS Independent
Classifier: Programming Language :: Python :: 3
Classifier: Programming Language :: Python :: 3.10
Classifier: Programming Language :: Python :: 3.11
Classifier: Programming Language :: Python :: 3.12
Classifier: Topic :: Security
Classifier: Topic :: Utilities
Requires-Dist: colorama (>=0.4.6,<0.5.0)
Requires-Dist: coloredlogs (>=15.0,<16.0)
Requires-Dist: flask (==2.0.3)
Requires-Dist: flask-socketio (>=4.2.1,<5.0.0)
Requires-Dist: psutil (>=5.9.8,<6.0.0)
Requires-Dist: pyinquirer (>=1.0.3,<2.0.0)
Requires-Dist: python-dotenv (>=1.0.1,<2.0.0)
Requires-Dist: terminaltables (>=3.1.0,<4.0.0)
Requires-Dist: werkzeug (==2.0.3)
Project-URL: Repository, https://github.com/grapheneX/grapheneX
